{
  "ticker": "APO",
  "generated_at": "2026-06-25T18:06:45.991277",
  "score": {
    "final_score": 35.3,
    "rating": "Drop",
    "confidence": 26.83,
    "risk_level": "Moderate",
    "categories": {
      "technical": 43.0,
      "momentum": 25.0,
      "volume": 0,
      "fundamental": 47.0,
      "risk": 60.0,
      "catalyst": 45.0
    },
    "technical": {
      "score": 43.0,
      "evidence": [
        "SMA alignment is constructive",
        "EMA trend is positive",
        "Stock is not materially extended from SMA20"
      ],
      "support": 104.27999877929688,
      "resistance": 138.91000366210938,
      "risk_reward": 0.94
    },
    "momentum": {
      "score": 25.0,
      "returns": {
        "1m": -0.06011858184764418,
        "3m": 0.11671121144802865,
        "6m": -0.1731091977606214,
        "12m": -0.1133421201927125
      },
      "acceleration": 0.2033,
      "evidence": [
        "3m return is positive",
        "Momentum is accelerating"
      ]
    },
    "volume": {
      "score": 0,
      "average_volume": 3656648.05,
      "relative_volume": 0.4713499840379771,
      "accumulation_days": 4,
      "distribution_days": 5,
      "evidence": []
    },
    "fundamental": {
      "score": 47.0,
      "classification": "Fundamentally Weak",
      "evidence": []
    },
    "risk": {
      "score": 60.0,
      "risk_metrics": {
        "volatility": 0.02531423877858924,
        "annualized_volatility": 0.40185108262232755,
        "maximum_drawdown": -0.42821269818585583,
        "sharpe_ratio": 0.27571691645777197,
        "sortino_ratio": 0.3596405622711213,
        "calmar_ratio": 0.07089814284898797,
        "beta": 1.5642818595474823,
        "alpha": -0.1629804499322242,
        "capm_expected_return": 0.27377759130806967,
        "actual_return": 0.11079714137584548,
        "market_return": 0.17501806956149732
      },
      "evidence": [
        "Historical drawdown is severe",
        "Beta indicates elevated market sensitivity"
      ]
    },
    "catalyst": {
      "score": 45.0,
      "evidence": [
        "analyst revision",
        "insider buying",
        "guidance change"
      ]
    },
    "explanation": "SMA alignment is constructive; EMA trend is positive; Stock is not materially extended from SMA20; 3m return is positive; Momentum is accelerating; analyst revision"
  },
  "fundamentals": {
    "ticker": "APO",
    "available": true,
    "company_name": "Apollo Global Management, Inc.",
    "sector": "Financial Services",
    "industry": "Asset Management",
    "exchange": "NYQ",
    "market_cap": 70606102528.0,
    "revenue_growth": -0.092,
    "eps_growth": null,
    "fcf_growth": null,
    "ebitda_growth": null,
    "gross_margin": 0.35222,
    "operating_margin": 0.13489,
    "net_margin": 0.03656,
    "roe": 0.08492,
    "roa": 0.00708,
    "roic": null,
    "debt_to_equity": 1.01267,
    "current_ratio": 2.024,
    "quick_ratio": 1.98,
    "cash_position": 41946001408.0,
    "total_debt": 40034000896.0,
    "interest_coverage": null,
    "forward_pe": 11.54097,
    "trailing_pe": 77.025154,
    "peg": 0.72,
    "price_to_book": 3.8055437,
    "price_to_sales": 2.2567234,
    "enterprise_to_ebitda": null,
    "enterprise_to_revenue": 2.869,
    "fcf_yield": null,
    "institutional_ownership": 0.71786004,
    "insider_ownership": 0.27141002,
    "short_interest": 30285699.0,
    "short_ratio": 8.82,
    "short_percent_float": 0.0573,
    "days_to_cover": 8.82,
    "target_mean_price": 150.375,
    "target_high_price": 173.0,
    "target_low_price": 125.0,
    "recommendation": "buy",
    "number_of_analysts": 16.0,
    "dividend_yield": 1.84,
    "payout_ratio": 1.283,
    "next_earnings_date": "1778070600",
    "eps_current_year": 1.59,
    "eps_forward": 10.61176,
    "classification": "Fundamentally Weak",
    "from_cache": true
  },
  "technical_screen": {
    "rsi": 40.19271984664374,
    "macd_cross": false,
    "breakout": false,
    "new_52w_high": false,
    "relative_volume": 0.4713499840379771,
    "price_above_sma50": false,
    "price_above_sma200": false,
    "setup_type": "No clear setup",
    "support": 104.27999877929688,
    "resistance": 138.91000366210938
  },
  "earnings": {
    "next_earnings_date": "1778070600",
    "surprise_tracking": "Available",
    "beat_streak": 4,
    "miss_streak": 0,
    "average_surprise_pct": 0.11,
    "last_surprise_pct": 0.0292,
    "last_surprise_direction": "beat",
    "risk_score": 65,
    "history": [
      {
        "date": "2026-03-31",
        "eps_estimate": 1.88494,
        "eps_actual": 1.94,
        "surprise_pct": 0.0292,
        "beat": true
      },
      {
        "date": "2025-12-31",
        "eps_estimate": 2.0366,
        "eps_actual": 2.47,
        "surprise_pct": 0.21280001,
        "beat": true
      },
      {
        "date": "2025-09-30",
        "eps_estimate": 1.90008,
        "eps_actual": 2.17,
        "surprise_pct": 0.1421,
        "beat": true
      },
      {
        "date": "2025-06-30",
        "eps_estimate": 1.84339,
        "eps_actual": 1.92,
        "surprise_pct": 0.0416,
        "beat": true
      }
    ]
  },
  "catalysts": {
    "earnings_surprise": false,
    "analyst_revision": true,
    "insider_buying": true,
    "sector_strength": false,
    "major_news": false,
    "guidance_change": true,
    "bullish_news_score": 0,
    "bearish_news_score": 0,
    "institutional_ownership": 0.71786004,
    "detail": {
      "earnings": {
        "available": true,
        "history": [
          {
            "date": "2026-03-31",
            "eps_estimate": 1.88494,
            "eps_actual": 1.94,
            "surprise_pct": 0.0292,
            "beat": true
          },
          {
            "date": "2025-12-31",
            "eps_estimate": 2.0366,
            "eps_actual": 2.47,
            "surprise_pct": 0.21280001,
            "beat": true
          },
          {
            "date": "2025-09-30",
            "eps_estimate": 1.90008,
            "eps_actual": 2.17,
            "surprise_pct": 0.1421,
            "beat": true
          },
          {
            "date": "2025-06-30",
            "eps_estimate": 1.84339,
            "eps_actual": 1.92,
            "surprise_pct": 0.0416,
            "beat": true
          }
        ],
        "beat_streak": 4,
        "miss_streak": 0,
        "average_surprise_pct": 0.11,
        "last_surprise_pct": 0.0292,
        "last_surprise_direction": "beat"
      },
      "analyst_upside_pct": 23.14,
      "eps_growth_implied": 567.41
    },
    "evidence": [
      "analyst target/recommendation data is supportive",
      "insider ownership or purchase data is supportive",
      "news tone or forward EPS implies a catalyst shift"
    ]
  },
  "analyst": {
    "consensus": "buy",
    "target_mean_price": 150.375,
    "target_high_price": 173.0,
    "target_low_price": 125.0,
    "number_of_analysts": 16.0
  },
  "insider_short_interest": {
    "insider_ownership": 0.27141002,
    "institutional_ownership": 0.71786004,
    "short_interest": 30285699.0,
    "short_percent_float": 0.0573,
    "days_to_cover": 8.82,
    "insider_transactions": "Unavailable from current data provider."
  },
  "news": {
    "available": true,
    "items": [
      {
        "headline": "Lower oil prices may be the Fed's next problem: Chart of the Day",
        "source": "Yahoo Finance",
        "published": "2026-06-25T10:00:00Z",
        "summary": "Lower oil prices may mean a new problem for investors and the Fed.",
        "bullish_score": 0,
        "bearish_score": 0,
        "importance_score": 30,
        "why_it_matters": "News impact is unclear; monitor price and volume reaction."
      },
      {
        "headline": "Ares Caps Private-Credit Fund Redemptions Again as 14% Seek Exits",
        "source": "Barrons.com",
        "published": "2026-06-25T16:12:00Z",
        "summary": "Ares Management limited withdrawals from its Strategic Income Fund after investors sought to redeem 14.4% of shares, though the firm expects to clear its redemption backlog by year-end.",
        "bullish_score": 0,
        "bearish_score": 0,
        "importance_score": 30,
        "why_it_matters": "News impact is unclear; monitor price and volume reaction."
      },
      {
        "headline": "Apollo Caps Private Credit Fund Withdrawals After Requests Near 17%",
        "source": "The Daily Upside",
        "published": "2026-06-24T04:01:00Z",
        "summary": "The firm estimates that gross outflows from Apollo Debt Solutions will be roughly $700 million for the quarter.",
        "bullish_score": 0,
        "bearish_score": 0,
        "importance_score": 30,
        "why_it_matters": "News impact is unclear; monitor price and volume reaction."
      },
      {
        "headline": "Sector Update: Financial Stocks Advance Late Afternoon",
        "source": "MT Newswires",
        "published": "2026-06-23T19:45:09Z",
        "summary": "Financial stocks were increasing in late Tuesday afternoon trading, with the NYSE Financial Index an",
        "bullish_score": 0,
        "bearish_score": 0,
        "importance_score": 30,
        "why_it_matters": "News impact is unclear; monitor price and volume reaction."
      },
      {
        "headline": "Apollo Caps Private Credit Fund After 17% Request to Exit",
        "source": "Wealth Management",
        "published": "2026-06-23T18:19:09Z",
        "summary": "Apollo Debt Solutions capped withdrawals at 5% of outstanding shares on Monday after investors asked to redeem 16.8%, according to a shareholder letter.",
        "bullish_score": 0,
        "bearish_score": 0,
        "importance_score": 30,
        "why_it_matters": "News impact is unclear; monitor price and volume reaction."
      }
    ]
  },
  "sentiment": {
    "available": false,
    "note": "Social sentiment sources are not configured."
  },
  "options_flow": {
    "available": false,
    "note": "Options flow scan requires a dedicated options-chain pass."
  },
  "portfolio_fit": {
    "available": true,
    "sector": null,
    "current_sector_weight": 0,
    "assessment": "Potential diversifier; evaluate correlation and volatility before adding."
  },
  "probability": {
    "model": "rules_to_probability_v1",
    "probability_of_outperformance": 0.5142,
    "probability_pct": 51.42,
    "confidence": "High",
    "evidence": [
      "Analyst data is supportive",
      "Composite score 35.3/100"
    ],
    "note": "Heuristic probability until enough labeled outcomes exist for trained ML."
  },
  "features": {
    "final_score": 35.3,
    "technical_score": 43.0,
    "momentum_score": 25.0,
    "volume_score": 0,
    "fundamental_score": 47.0,
    "risk_score": 60.0,
    "catalyst_score": 45.0,
    "revenue_growth": -0.092,
    "eps_growth": null,
    "roe": 0.08492,
    "forward_pe": 11.54097,
    "relative_volume": 0.4713499840379771,
    "breakout": false,
    "price_above_sma50": false,
    "price_above_sma200": false,
    "earnings_surprise": false,
    "analyst_revision": true,
    "major_news": false
  },
  "quant_model": {
    "returns": {
      "daily": -0.004078303476533374,
      "weekly": -0.12101364008943272,
      "monthly": -0.06011858184764418,
      "annual": -0.1133421201927125
    },
    "risk": {
      "volatility": 0.02531423877858924,
      "annualized_volatility": 0.40185108262232755,
      "maximum_drawdown": -0.42821269818585583,
      "sharpe_ratio": 0.27571691645777197,
      "sortino_ratio": 0.3596405622711213,
      "calmar_ratio": 0.07089814284898797,
      "beta": 1.5642818595474823,
      "alpha": -0.1629804499322242,
      "capm_expected_return": 0.27377759130806967,
      "actual_return": 0.11079714137584548,
      "market_return": 0.17501806956149732
    },
    "capm": {
      "beta": 1.5642818595474823,
      "alpha": -0.1629804499322242,
      "capm_expected_return": 0.27377759130806967,
      "actual_return": 0.11079714137584548,
      "market_return": 0.17501806956149732,
      "interpretation": "Beta 1.56: Moves roughly 56% more than the market. CAPM expected return is 27.38%; realized alpha is -16.30%, meaning negative alpha versus CAPM."
    },
    "factor_decomposition": {
      "actual_return": 0.11079714137584548,
      "components": {
        "market_component": 0.27377759130806967,
        "momentum_component": 0.0,
        "volatility_drag": -0.03037021652446551,
        "alpha_component": -0.1629804499322242
      },
      "component_weights_pct": {
        "market_component": 58.61,
        "momentum_component": 0.0,
        "volatility_drag": 6.5,
        "alpha_component": 34.89
      },
      "interpretation": "Decomposes realized return into market risk, momentum proxy, volatility drag, and residual alpha. This is a research approximation, not proof of causality."
    },
    "trend": {
      "sma20": 130.7355007171631,
      "sma50": 129.21505935668947,
      "sma200": 127.73506523132325,
      "ema20": 130.6872290025005,
      "ema50": 128.120899915083,
      "ema200": 127.94309797078199
    },
    "momentum": {
      "3m": 0.11671121144802865,
      "6m": -0.1731091977606214,
      "12m": -0.1133421201927125,
      "24m": 0.0,
      "score": 25.0
    },
    "volume": {
      "average_volume": 3656648.05,
      "relative_volume": 0.4713499840379771,
      "volume_spike": false
    },
    "volatility_regime": "Normal volatility",
    "quant_score": {
      "score": 40,
      "label": "Neutral"
    }
  },
  "why_now": {
    "send_alert": false,
    "reason": "No clear Why Now trigger",
    "evidence": "No recent statistically meaningful change was detected.",
    "date_of_change": "2026-06-25",
    "strength": 0,
    "invalidates": "N/A",
    "triggers": []
  },
  "report": "Ticker: APO\nRating: Drop | Score: 35.3/100 | Confidence: 26.83/100\nBull Case: No decisive bull case yet.\nBear Case: volume confirmation is weak\nTechnical Outlook: No clear setup | Support: 104.27999877929688 | Resistance: 138.91000366210938\nFundamental Outlook: Fundamentally Weak | Forward P/E: 11.54097\nNews/Catalyst: Lower oil prices may be the Fed's next problem: Chart of the Day\nPortfolio Fit: Potential diversifier; evaluate correlation and volatility before adding.\nWhy Now: No clear Why Now trigger | Evidence: No recent statistically meaningful change was detected.\nWhat Invalidates: N/A"
}