{
  "ticker": "AVGO",
  "generated_at": "2026-06-16T17:58:32.013665",
  "score": {
    "final_score": 61.4,
    "rating": "Hold",
    "confidence": 56.25,
    "risk_level": "Moderate",
    "categories": {
      "technical": 55.0,
      "momentum": 75.0,
      "volume": 25.0,
      "fundamental": 86.0,
      "risk": 60.0,
      "catalyst": 65.0
    },
    "technical": {
      "score": 55.0,
      "evidence": [
        "Price above SMA200",
        "SMA alignment is constructive",
        "EMA trend is positive",
        "Stock is not materially extended from SMA20"
      ],
      "support": 293.4100036621094,
      "resistance": 481.57000732421875,
      "risk_reward": 1.17
    },
    "momentum": {
      "score": 75.0,
      "returns": {
        "1m": -0.10638776925469762,
        "3m": 0.1849989996807735,
        "6m": 0.05987433408643206,
        "12m": 0.5401430856128071
      },
      "acceleration": 0.1551,
      "evidence": [
        "3m return is positive",
        "6m return is positive",
        "12m return is positive",
        "Momentum is accelerating",
        "Outperforming S&P 500 over 3 months"
      ]
    },
    "volume": {
      "score": 25.0,
      "average_volume": 32063550.2,
      "relative_volume": 0.4661774478111286,
      "accumulation_days": 7,
      "distribution_days": 6,
      "evidence": [
        "Accumulation days exceed distribution days"
      ]
    },
    "fundamental": {
      "score": 86.0,
      "classification": "Quality Compounder",
      "evidence": [
        "revenue growth is strong",
        "eps growth is strong"
      ]
    },
    "risk": {
      "score": 60.0,
      "risk_metrics": {
        "volatility": 0.03426400962083525,
        "annualized_volatility": 0.5439242902599276,
        "maximum_drawdown": -0.41149676738581364,
        "sharpe_ratio": 0.9650367196165027,
        "sortino_ratio": 1.4118469637967448,
        "calmar_ratio": 1.1188348856926997,
        "beta": 2.0110628176422547,
        "alpha": 0.1489836694979254
      },
      "evidence": [
        "Historical drawdown is severe",
        "Beta indicates elevated market sensitivity"
      ]
    },
    "catalyst": {
      "score": 65.0,
      "evidence": [
        "earnings surprise",
        "analyst revision",
        "major news",
        "guidance change"
      ]
    },
    "explanation": "Price above SMA200; SMA alignment is constructive; EMA trend is positive; Stock is not materially extended from SMA20; 3m return is positive; 6m return is positive"
  },
  "fundamentals": {
    "ticker": "AVGO",
    "available": true,
    "company_name": "Broadcom Inc.",
    "sector": "Technology",
    "industry": "Semiconductors",
    "exchange": "NMS",
    "market_cap": 1806952693760.0,
    "revenue_growth": 0.479,
    "eps_growth": 0.854,
    "fcf_growth": null,
    "ebitda_growth": null,
    "gross_margin": 0.76284,
    "operating_margin": 0.48988,
    "net_margin": 0.38848,
    "roe": 0.37280998,
    "roa": 0.121190004,
    "roic": null,
    "debt_to_equity": 0.7401800000000001,
    "current_ratio": 2.238,
    "quick_ratio": 1.929,
    "cash_position": 19627999232.0,
    "total_debt": 64907001856.0,
    "interest_coverage": null,
    "forward_pe": 19.627699,
    "trailing_pe": 62.9859,
    "peg": 0.69,
    "price_to_book": 20.607975,
    "price_to_sales": 23.944248,
    "enterprise_to_ebitda": 45.611,
    "enterprise_to_revenue": 25.435,
    "fcf_yield": 0.015059746268938206,
    "institutional_ownership": 0.79913,
    "insider_ownership": 0.0194,
    "short_interest": 58477285.0,
    "short_ratio": 3.01,
    "short_percent_float": 0.0125,
    "days_to_cover": 3.01,
    "target_mean_price": 522.06226,
    "target_high_price": 650.0,
    "target_low_price": 215.88,
    "recommendation": "strong_buy",
    "number_of_analysts": 45.0,
    "dividend_yield": 0.66,
    "payout_ratio": 0.41259998,
    "next_earnings_date": "1780516800",
    "eps_current_year": 6.03,
    "eps_forward": 19.35046,
    "classification": "Quality Compounder"
  },
  "technical_screen": {
    "rsi": 41.036173140904644,
    "macd_cross": false,
    "breakout": false,
    "new_52w_high": false,
    "relative_volume": 0.4661774478111286,
    "price_above_sma50": false,
    "price_above_sma200": true,
    "setup_type": "No clear setup",
    "support": 293.4100036621094,
    "resistance": 481.57000732421875
  },
  "earnings": {
    "next_earnings_date": "1780516800",
    "surprise_tracking": "Available",
    "beat_streak": 4,
    "miss_streak": 0,
    "average_surprise_pct": 0.02,
    "last_surprise_pct": 0.0178,
    "last_surprise_direction": "beat",
    "risk_score": 65,
    "history": [
      {
        "date": "2026-04-30",
        "eps_estimate": 2.39724,
        "eps_actual": 2.44,
        "surprise_pct": 0.0178,
        "beat": true
      },
      {
        "date": "2026-01-31",
        "eps_estimate": 2.02326,
        "eps_actual": 2.05,
        "surprise_pct": 0.013200001,
        "beat": true
      },
      {
        "date": "2025-10-31",
        "eps_estimate": 1.86817,
        "eps_actual": 1.95,
        "surprise_pct": 0.0438,
        "beat": true
      },
      {
        "date": "2025-07-31",
        "eps_estimate": 1.66338,
        "eps_actual": 1.69,
        "surprise_pct": 0.016,
        "beat": true
      }
    ]
  },
  "catalysts": {
    "earnings_surprise": true,
    "analyst_revision": true,
    "insider_buying": false,
    "sector_strength": false,
    "major_news": true,
    "guidance_change": true,
    "bullish_news_score": 6,
    "bearish_news_score": 0,
    "institutional_ownership": 0.79913,
    "detail": {
      "earnings": {
        "available": true,
        "history": [
          {
            "date": "2026-04-30",
            "eps_estimate": 2.39724,
            "eps_actual": 2.44,
            "surprise_pct": 0.0178,
            "beat": true
          },
          {
            "date": "2026-01-31",
            "eps_estimate": 2.02326,
            "eps_actual": 2.05,
            "surprise_pct": 0.013200001,
            "beat": true
          },
          {
            "date": "2025-10-31",
            "eps_estimate": 1.86817,
            "eps_actual": 1.95,
            "surprise_pct": 0.0438,
            "beat": true
          },
          {
            "date": "2025-07-31",
            "eps_estimate": 1.66338,
            "eps_actual": 1.69,
            "surprise_pct": 0.016,
            "beat": true
          }
        ],
        "beat_streak": 4,
        "miss_streak": 0,
        "average_surprise_pct": 0.02,
        "last_surprise_pct": 0.0178,
        "last_surprise_direction": "beat"
      },
      "analyst_upside_pct": 37.46,
      "eps_growth_implied": 220.9
    },
    "evidence": [
      "recent earnings surprise or earnings growth is positive",
      "analyst target/recommendation data is supportive",
      "recent news item has elevated importance",
      "news tone or forward EPS implies a catalyst shift"
    ]
  },
  "analyst": {
    "consensus": "strong_buy",
    "target_mean_price": 522.06226,
    "target_high_price": 650.0,
    "target_low_price": 215.88,
    "number_of_analysts": 45.0
  },
  "insider_short_interest": {
    "insider_ownership": 0.0194,
    "institutional_ownership": 0.79913,
    "short_interest": 58477285.0,
    "short_percent_float": 0.0125,
    "days_to_cover": 3.01,
    "insider_transactions": "Unavailable from current data provider."
  },
  "news": {
    "available": true,
    "items": [
      {
        "headline": "Why Is the US Stock Market Down Today?",
        "source": "BeInCrypto",
        "published": "2026-06-16T17:21:11Z",
        "summary": "US stocks split as the Iran oil deal lifted the Dow to a record while chip selling dragged the S&P 500 and Nasdaq lower.",
        "bullish_score": 1,
        "bearish_score": 0,
        "importance_score": 45,
        "why_it_matters": "News appears more supportive of sentiment or growth expectations."
      },
      {
        "headline": "Micron Stock Slips From Record High. Where It Goes Next.",
        "source": "Barrons.com",
        "published": "2026-06-16T16:22:00Z",
        "summary": "Micron stock has had 34 record closes so far in 2026 and Wall Street is racing to raise price targets for the memory-chip maker.",
        "bullish_score": 2,
        "bearish_score": 0,
        "importance_score": 60,
        "why_it_matters": "News appears more supportive of sentiment or growth expectations."
      },
      {
        "headline": "Down More Than 20% From Its High, Is Broadcom Stock a Buy?",
        "source": "Motley Fool",
        "published": "2026-06-16T14:50:00Z",
        "summary": "The tech giant's valuation has fallen since it reported earnings earlier this month.",
        "bullish_score": 0,
        "bearish_score": 0,
        "importance_score": 30,
        "why_it_matters": "News impact is unclear; monitor price and volume reaction."
      },
      {
        "headline": "CRDO vs. AVGO: Which Data Center Connectivity Stock Is the Smart Buy?",
        "source": "Zacks",
        "published": "2026-06-16T14:11:00Z",
        "summary": "CRDO's AI connectivity momentum, optical growth outlook and margin gains make it stand out, but AVGO's scale and profitability keep the race tight.",
        "bullish_score": 2,
        "bearish_score": 0,
        "importance_score": 60,
        "why_it_matters": "News appears more supportive of sentiment or growth expectations."
      },
      {
        "headline": "Marvell Needs Lots of Growth to Achieve Huang\u2019s $1 Trillion Call",
        "source": "Bloomberg",
        "published": "2026-06-16T13:42:40Z",
        "summary": "(Bloomberg) -- Jensen Huang may see Marvell Technology Inc. as the stock market\u2019s \u201cnext trillion-dollar company,\u201d but it\u2019s going to take a lot of growth for the chipmaker to even sniff that lofty level. Most Read from BloombergIran\u2019s Deputy Foreign Minister Confirms Deal Reached With USNetanyahu Pays a Political Price for Trump\u2019s Iran DealStudios in Microsoft\u2019s Xbox Division Brace for ClosuresSpaceX Cements $60 Billion Cursor Takeover Following IPOUS and Iran Agree to Halt War, Restart Middle Ea",
        "bullish_score": 1,
        "bearish_score": 0,
        "importance_score": 45,
        "why_it_matters": "News appears more supportive of sentiment or growth expectations."
      }
    ]
  },
  "sentiment": {
    "available": false,
    "note": "Social sentiment sources are not configured."
  },
  "options_flow": {
    "available": false,
    "note": "Options flow scan requires a dedicated options-chain pass."
  },
  "portfolio_fit": {
    "available": true,
    "sector": null,
    "current_sector_weight": 0,
    "assessment": "Potential diversifier; evaluate correlation and volatility before adding."
  },
  "why_now": {
    "send_alert": false,
    "reason": "No clear Why Now trigger",
    "evidence": "No recent statistically meaningful change was detected.",
    "date_of_change": "2026-06-16",
    "strength": 0,
    "invalidates": "N/A",
    "triggers": []
  },
  "report": "Ticker: AVGO\nRating: Hold | Score: 61.4/100 | Confidence: 56.25/100\nBull Case: momentum and relative strength are constructive, fundamentals screen as Quality Compounder\nBear Case: volume confirmation is weak\nTechnical Outlook: No clear setup | Support: 293.4100036621094 | Resistance: 481.57000732421875\nFundamental Outlook: Quality Compounder | Forward P/E: 19.627699\nNews/Catalyst: Why Is the US Stock Market Down Today?\nPortfolio Fit: Potential diversifier; evaluate correlation and volatility before adding.\nWhy Now: No clear Why Now trigger | Evidence: No recent statistically meaningful change was detected.\nWhat Invalidates: N/A"
}