{
  "ticker": "CAH",
  "generated_at": "2026-06-15T23:00:11.641361",
  "score": {
    "final_score": 59.75,
    "rating": "Hold",
    "confidence": 51.78,
    "risk_level": "Controlled",
    "categories": {
      "technical": 65.0,
      "momentum": 60.0,
      "volume": 25.0,
      "fundamental": 50.0,
      "risk": 100,
      "catalyst": 45.0
    },
    "technical": {
      "score": 65.0,
      "evidence": [
        "Price above SMA20",
        "Price above SMA50",
        "Price above SMA200",
        "SMA alignment is constructive",
        "EMA trend is positive",
        "MACD is above signal",
        "Stock is extended from SMA20"
      ],
      "support": 182.5,
      "resistance": 226.39999389648438,
      "risk_reward": 0.0
    },
    "momentum": {
      "score": 60.0,
      "returns": {
        "1m": 0.16472882091435292,
        "3m": 0.043011230400856304,
        "6m": 0.1472092977044217,
        "12m": 0.4263274592561297
      },
      "acceleration": -0.0306,
      "evidence": [
        "1m return is positive",
        "3m return is positive",
        "6m return is positive",
        "12m return is positive"
      ]
    },
    "volume": {
      "score": 25.0,
      "average_volume": 2163376.8,
      "relative_volume": 0.8125889119269468,
      "accumulation_days": 4,
      "distribution_days": 1,
      "evidence": [
        "Accumulation days exceed distribution days"
      ]
    },
    "fundamental": {
      "score": 50.0,
      "classification": "Fundamentally Average",
      "evidence": [
        "revenue growth is strong"
      ]
    },
    "risk": {
      "score": 100,
      "risk_metrics": {
        "volatility": 0.016682963331480435,
        "annualized_volatility": 0.26483383264024113,
        "maximum_drawdown": -0.2041831168239242,
        "sharpe_ratio": 1.726483567418007,
        "sortino_ratio": 2.6466535880966116,
        "calmar_ratio": 2.574978552535872,
        "beta": 0.2915865194602835,
        "alpha": 0.40214036534267994
      },
      "evidence": []
    },
    "catalyst": {
      "score": 45.0,
      "evidence": [
        "sector strength",
        "major news",
        "guidance change"
      ]
    },
    "explanation": "Price above SMA20; Price above SMA50; Price above SMA200; SMA alignment is constructive; EMA trend is positive; MACD is above signal"
  },
  "fundamentals": {
    "ticker": "CAH",
    "available": true,
    "company_name": "Cardinal Health, Inc.",
    "sector": "Healthcare",
    "industry": "Medical Distribution",
    "exchange": "NYQ",
    "market_cap": 52806393856.0,
    "revenue_growth": 0.11,
    "eps_growth": -0.195,
    "fcf_growth": null,
    "ebitda_growth": null,
    "gross_margin": 0.037550002,
    "operating_margin": 0.01413,
    "net_margin": 0.0062,
    "roe": null,
    "roa": 0.03601,
    "roic": null,
    "debt_to_equity": null,
    "current_ratio": 0.907,
    "quick_ratio": 0.419,
    "cash_position": 3936999936.0,
    "total_debt": 8915999744.0,
    "interest_coverage": null,
    "forward_pe": 18.794178,
    "trailing_pe": 34.370426,
    "peg": 1.39,
    "price_to_book": -18.709652,
    "price_to_sales": 0.2106064,
    "enterprise_to_ebitda": 14.413,
    "enterprise_to_revenue": 0.23,
    "fcf_yield": 0.09184493614969563,
    "institutional_ownership": 0.89880997,
    "insider_ownership": 0.00259,
    "short_interest": 7906193.0,
    "short_ratio": 3.1,
    "short_percent_float": 0.039,
    "days_to_cover": 3.1,
    "target_mean_price": 245.26666,
    "target_high_price": 275.0,
    "target_low_price": 215.0,
    "recommendation": "strong_buy",
    "number_of_analysts": 15.0,
    "dividend_yield": 0.91,
    "payout_ratio": 0.31190002,
    "next_earnings_date": "1777552200",
    "eps_current_year": 6.56,
    "eps_forward": 11.9968,
    "classification": "Fundamentally Average",
    "from_cache": true
  },
  "technical_screen": {
    "rsi": 82.95769194804673,
    "macd_cross": false,
    "breakout": true,
    "new_52w_high": false,
    "relative_volume": 0.8125889119269468,
    "price_above_sma50": true,
    "price_above_sma200": true,
    "setup_type": "52-week high pressure, trend continuation",
    "support": 182.5,
    "resistance": 226.39999389648438
  },
  "earnings": {
    "next_earnings_date": "1777552200",
    "surprise_tracking": "Available",
    "beat_streak": 4,
    "miss_streak": 0,
    "average_surprise_pct": 0.11,
    "last_surprise_pct": 0.137,
    "last_surprise_direction": "beat",
    "risk_score": 65,
    "history": [
      {
        "date": "2026-03-31",
        "eps_estimate": 2.78816,
        "eps_actual": 3.17,
        "surprise_pct": 0.137,
        "beat": true
      },
      {
        "date": "2025-12-31",
        "eps_estimate": 2.36572,
        "eps_actual": 2.63,
        "surprise_pct": 0.1117,
        "beat": true
      },
      {
        "date": "2025-09-30",
        "eps_estimate": 2.16845,
        "eps_actual": 2.55,
        "surprise_pct": 0.176,
        "beat": true
      },
      {
        "date": "2025-06-30",
        "eps_estimate": 2.03214,
        "eps_actual": 2.08,
        "surprise_pct": 0.023599999,
        "beat": true
      }
    ]
  },
  "catalysts": {
    "earnings_surprise": false,
    "analyst_revision": false,
    "insider_buying": false,
    "sector_strength": true,
    "major_news": true,
    "guidance_change": true,
    "bullish_news_score": 7,
    "bearish_news_score": 1,
    "institutional_ownership": 0.89880997,
    "detail": {
      "earnings": {
        "available": true,
        "history": [
          {
            "date": "2026-03-31",
            "eps_estimate": 2.78816,
            "eps_actual": 3.17,
            "surprise_pct": 0.137,
            "beat": true
          },
          {
            "date": "2025-12-31",
            "eps_estimate": 2.36572,
            "eps_actual": 2.63,
            "surprise_pct": 0.1117,
            "beat": true
          },
          {
            "date": "2025-09-30",
            "eps_estimate": 2.16845,
            "eps_actual": 2.55,
            "surprise_pct": 0.176,
            "beat": true
          },
          {
            "date": "2025-06-30",
            "eps_estimate": 2.03214,
            "eps_actual": 2.08,
            "surprise_pct": 0.023599999,
            "beat": true
          }
        ],
        "beat_streak": 4,
        "miss_streak": 0,
        "average_surprise_pct": 0.11,
        "last_surprise_pct": 0.137,
        "last_surprise_direction": "beat"
      },
      "analyst_upside_pct": 8.33,
      "eps_growth_implied": 82.88
    },
    "evidence": [
      "technical backdrop is constructive",
      "recent news item has elevated importance",
      "news tone or forward EPS implies a catalyst shift"
    ]
  },
  "analyst": {
    "consensus": "strong_buy",
    "target_mean_price": 245.26666,
    "target_high_price": 275.0,
    "target_low_price": 215.0,
    "number_of_analysts": 15.0
  },
  "insider_short_interest": {
    "insider_ownership": 0.00259,
    "institutional_ownership": 0.89880997,
    "short_interest": 7906193.0,
    "short_percent_float": 0.039,
    "days_to_cover": 3.1,
    "insider_transactions": "Unavailable from current data provider."
  },
  "news": {
    "available": true,
    "items": [
      {
        "headline": "Cardinal Health Stock: Is CAH Outperforming the Healthcare Sector?",
        "source": "Barchart",
        "published": "2026-06-15T15:47:26Z",
        "summary": "Cardinal Health has outperformed the healthcare sector over the past year. Moreover, Wall Street analysts are strongly bullish on the stock.",
        "bullish_score": 1,
        "bearish_score": 0,
        "importance_score": 45,
        "why_it_matters": "News appears more supportive of sentiment or growth expectations."
      },
      {
        "headline": "Here's Why You Should Hold Stryker Stock in Your Portfolio for Now",
        "source": "Zacks",
        "published": "2026-06-12T17:16:00Z",
        "summary": "Stryker faces cyberattack fallout, but strong procedure demand, record Mako adoption and global expansion continue to support long-term growth.",
        "bullish_score": 3,
        "bearish_score": 0,
        "importance_score": 75,
        "why_it_matters": "News appears more supportive of sentiment or growth expectations."
      },
      {
        "headline": "Is Cardinal Health (CAH) Stock Undervalued Right Now?",
        "source": "Zacks",
        "published": "2026-06-12T13:40:03Z",
        "summary": "Here at Zacks, our focus is on the proven Zacks Rank system, which emphasizes earnings estimates and estimate revisions to find great stocks. Nevertheless, we are always paying attention to the latest value, growth, and momentum trends to underscore strong picks.",
        "bullish_score": 2,
        "bearish_score": 0,
        "importance_score": 60,
        "why_it_matters": "News appears more supportive of sentiment or growth expectations."
      },
      {
        "headline": "2 Dirt Cheap Healthcare Stocks to Buy With $1,000 Right Now",
        "source": "Motley Fool",
        "published": "2026-06-09T15:05:00Z",
        "summary": "Italian healthcare vials and cartridges maker Stevanato Group and U.S. generic and wholesale pharmaceutical company Cencora are two of the best healthcare buys right now.",
        "bullish_score": 0,
        "bearish_score": 0,
        "importance_score": 30,
        "why_it_matters": "News impact is unclear; monitor price and volume reaction."
      },
      {
        "headline": "How The Mixed Analyst Calls Are Reframing The Cardinal Health (CAH) Investment Story",
        "source": "Simply Wall St.",
        "published": "2026-06-06T06:11:50Z",
        "summary": "Cardinal Health is back in focus as fresh Street research reshapes the price target conversation, with several firms trimming their targets while one raises its view and another starts coverage on a bullish footing. Those mixed calls reflect a split between analysts who see room for upside if execution holds and others who are more cautious about how much to pay for the stock right now. As you read on, you will see how to track these shifting views and what they might mean for your own...",
        "bullish_score": 1,
        "bearish_score": 1,
        "importance_score": 60,
        "why_it_matters": "News impact is unclear; monitor price and volume reaction."
      }
    ]
  },
  "sentiment": {
    "available": false,
    "note": "Social sentiment sources are not configured."
  },
  "options_flow": {
    "available": false,
    "note": "Options flow scan requires a dedicated options-chain pass."
  },
  "portfolio_fit": {
    "available": true,
    "sector": null,
    "current_sector_weight": 0,
    "assessment": "Potential diversifier; evaluate correlation and volatility before adding."
  },
  "why_now": {
    "send_alert": false,
    "reason": "No clear Why Now trigger",
    "evidence": "No recent statistically meaningful change was detected.",
    "date_of_change": "2026-06-15",
    "strength": 0,
    "invalidates": "N/A",
    "triggers": []
  },
  "report": "Ticker: CAH\nRating: Hold | Score: 59.75/100 | Confidence: 51.78/100\nBull Case: momentum and relative strength are constructive, price is pressing near breakout/high territory\nBear Case: volume confirmation is weak\nTechnical Outlook: 52-week high pressure, trend continuation | Support: 182.5 | Resistance: 226.39999389648438\nFundamental Outlook: Fundamentally Average | Forward P/E: 18.794178\nNews/Catalyst: Cardinal Health Stock: Is CAH Outperforming the Healthcare Sector?\nPortfolio Fit: Potential diversifier; evaluate correlation and volatility before adding.\nWhy Now: No clear Why Now trigger | Evidence: No recent statistically meaningful change was detected.\nWhat Invalidates: N/A"
}