{
  "ticker": "GOOG",
  "generated_at": "2026-06-16T17:59:22.055212",
  "score": {
    "final_score": 65.15,
    "rating": "Watch",
    "confidence": 53.98,
    "risk_level": "Controlled",
    "categories": {
      "technical": 57.0,
      "momentum": 75.0,
      "volume": 0,
      "fundamental": 86.0,
      "risk": 100,
      "catalyst": 85.0
    },
    "technical": {
      "score": 57.0,
      "evidence": [
        "Price above SMA50",
        "Price above SMA200",
        "SMA alignment is constructive",
        "EMA trend is positive",
        "Stock is not materially extended from SMA20"
      ],
      "support": 273.1400146484375,
      "resistance": 399.0400085449219,
      "risk_reward": 0.31
    },
    "momentum": {
      "score": 75.0,
      "returns": {
        "1m": -0.061395166265312384,
        "3m": 0.1931484057130568,
        "6m": 0.18972095604733008,
        "12m": 1.1037271704415619
      },
      "acceleration": 0.0983,
      "evidence": [
        "3m return is positive",
        "6m return is positive",
        "12m return is positive",
        "Momentum is accelerating",
        "Outperforming S&P 500 over 3 months"
      ]
    },
    "volume": {
      "score": 0,
      "average_volume": 23119449.3,
      "relative_volume": 0.35457098885136507,
      "accumulation_days": 3,
      "distribution_days": 6,
      "evidence": []
    },
    "fundamental": {
      "score": 86.0,
      "classification": "Quality Compounder",
      "evidence": [
        "revenue growth is strong",
        "eps growth is strong"
      ]
    },
    "risk": {
      "score": 100,
      "risk_metrics": {
        "volatility": 0.019061633454035862,
        "annualized_volatility": 0.3025940502122883,
        "maximum_drawdown": -0.29350043424171524,
        "sharpe_ratio": 1.3703604118798625,
        "sortino_ratio": 2.1731947608835744,
        "calmar_ratio": 1.5205764386779108,
        "beta": 1.0918681652816093,
        "alpha": 0.21056255877821017
      },
      "evidence": []
    },
    "catalyst": {
      "score": 85.0,
      "evidence": [
        "earnings surprise",
        "analyst revision",
        "insider buying",
        "sector strength",
        "guidance change"
      ]
    },
    "explanation": "Price above SMA50; Price above SMA200; SMA alignment is constructive; EMA trend is positive; Stock is not materially extended from SMA20; 3m return is positive"
  },
  "fundamentals": {
    "ticker": "GOOG",
    "available": true,
    "company_name": "Alphabet Inc.",
    "sector": "Communication Services",
    "industry": "Internet Content & Information",
    "exchange": "NMS",
    "market_cap": 4500796997632.0,
    "revenue_growth": 0.218,
    "eps_growth": 0.82,
    "fcf_growth": null,
    "ebitda_growth": null,
    "gross_margin": 0.60368,
    "operating_margin": 0.36121,
    "net_margin": 0.37919,
    "roe": 0.38884997,
    "roa": 0.14641,
    "roic": null,
    "debt_to_equity": 0.20026,
    "current_ratio": 1.922,
    "quick_ratio": 1.707,
    "cash_position": 126839996416.0,
    "total_debt": 95875997696.0,
    "interest_coverage": null,
    "forward_pe": 25.471302,
    "trailing_pe": 28.134249,
    "peg": 1.41,
    "price_to_book": 9.334413,
    "price_to_sales": 10.652824,
    "enterprise_to_ebitda": 27.381,
    "enterprise_to_revenue": 10.454,
    "fcf_yield": 0.0062037345898271895,
    "institutional_ownership": 0.61103,
    "insider_ownership": 0.06643,
    "short_interest": 43535503.0,
    "short_ratio": 2.2,
    "short_percent_float": null,
    "days_to_cover": 2.2,
    "target_mean_price": 409.00287,
    "target_high_price": 475.0,
    "target_low_price": 195.0,
    "recommendation": "strong_buy",
    "number_of_analysts": 14.0,
    "dividend_yield": 0.24,
    "payout_ratio": 0.0641,
    "next_earnings_date": "1777492800",
    "eps_current_year": 13.11,
    "eps_forward": 14.48061,
    "classification": "Quality Compounder"
  },
  "technical_screen": {
    "rsi": 39.96716101245575,
    "macd_cross": false,
    "breakout": false,
    "new_52w_high": false,
    "relative_volume": 0.35457098885136507,
    "price_above_sma50": true,
    "price_above_sma200": true,
    "setup_type": "trend continuation",
    "support": 273.1400146484375,
    "resistance": 399.0400085449219
  },
  "earnings": {
    "next_earnings_date": "1777492800",
    "surprise_tracking": "Available",
    "beat_streak": 4,
    "miss_streak": 0,
    "average_surprise_pct": 0.33,
    "last_surprise_pct": 0.943,
    "last_surprise_direction": "beat",
    "risk_score": 65,
    "history": [
      {
        "date": "2026-03-31",
        "eps_estimate": 2.62989,
        "eps_actual": 5.11,
        "surprise_pct": 0.943,
        "beat": true
      },
      {
        "date": "2025-12-31",
        "eps_estimate": 2.64089,
        "eps_actual": 2.82,
        "surprise_pct": 0.0678,
        "beat": true
      },
      {
        "date": "2025-09-30",
        "eps_estimate": 2.26206,
        "eps_actual": 2.87,
        "surprise_pct": 0.2688,
        "beat": true
      },
      {
        "date": "2025-06-30",
        "eps_estimate": 2.19807,
        "eps_actual": 2.31,
        "surprise_pct": 0.0509,
        "beat": true
      }
    ]
  },
  "catalysts": {
    "earnings_surprise": true,
    "analyst_revision": true,
    "insider_buying": true,
    "sector_strength": true,
    "major_news": false,
    "guidance_change": true,
    "bullish_news_score": 1,
    "bearish_news_score": 0,
    "institutional_ownership": 0.61103,
    "detail": {
      "earnings": {
        "available": true,
        "history": [
          {
            "date": "2026-03-31",
            "eps_estimate": 2.62989,
            "eps_actual": 5.11,
            "surprise_pct": 0.943,
            "beat": true
          },
          {
            "date": "2025-12-31",
            "eps_estimate": 2.64089,
            "eps_actual": 2.82,
            "surprise_pct": 0.0678,
            "beat": true
          },
          {
            "date": "2025-09-30",
            "eps_estimate": 2.26206,
            "eps_actual": 2.87,
            "surprise_pct": 0.2688,
            "beat": true
          },
          {
            "date": "2025-06-30",
            "eps_estimate": 2.19807,
            "eps_actual": 2.31,
            "surprise_pct": 0.0509,
            "beat": true
          }
        ],
        "beat_streak": 4,
        "miss_streak": 0,
        "average_surprise_pct": 0.33,
        "last_surprise_pct": 0.943,
        "last_surprise_direction": "beat"
      },
      "analyst_upside_pct": 10.89,
      "eps_growth_implied": 10.45
    },
    "evidence": [
      "recent earnings surprise or earnings growth is positive",
      "analyst target/recommendation data is supportive",
      "insider ownership or purchase data is supportive",
      "technical backdrop is constructive",
      "news tone or forward EPS implies a catalyst shift"
    ]
  },
  "analyst": {
    "consensus": "strong_buy",
    "target_mean_price": 409.00287,
    "target_high_price": 475.0,
    "target_low_price": 195.0,
    "number_of_analysts": 14.0
  },
  "insider_short_interest": {
    "insider_ownership": 0.06643,
    "institutional_ownership": 0.61103,
    "short_interest": 43535503.0,
    "short_percent_float": null,
    "days_to_cover": 2.2,
    "insider_transactions": "Unavailable from current data provider."
  },
  "news": {
    "available": true,
    "items": [
      {
        "headline": "SpaceX rockets past Amazon, eyes Microsoft in sprint toward $3 trillion",
        "source": "Yahoo Finance",
        "published": "2026-06-16T16:49:18Z",
        "summary": "SpaceX is one of the fastest new entrants ever into the top tier of the US market",
        "bullish_score": 0,
        "bearish_score": 0,
        "importance_score": 30,
        "why_it_matters": "News impact is unclear; monitor price and volume reaction."
      },
      {
        "headline": "Nvidia joins the AI funding wave as it plans a $20B bond sale: A closer look",
        "source": "Yahoo Finance Video",
        "published": "2026-06-15T20:00:21Z",
        "summary": "Nvidia (NVDA) is the latest hyperscaler to tap the debt market to fund its artificial intelligence (AI) build-out. Yahoo Finance Markets and Data Editor Jared Blikre discusses more in the video above.",
        "bullish_score": 0,
        "bearish_score": 0,
        "importance_score": 30,
        "why_it_matters": "News impact is unclear; monitor price and volume reaction."
      },
      {
        "headline": "Elon Musk could lose nearly $1 trillion and still be the world's richest person",
        "source": "Moneywise",
        "published": "2026-06-16T16:35:00Z",
        "summary": "Tuesday's spike in SpaceX stock boosted the fortune of the world's richest man by a cool $110 billion.",
        "bullish_score": 0,
        "bearish_score": 0,
        "importance_score": 30,
        "why_it_matters": "News impact is unclear; monitor price and volume reaction."
      },
      {
        "headline": "Jeff Bezos Just Raised $12 Billion. He\u2019s Betting His Newest Business Will Create the Next Elon Musk or Henry Ford",
        "source": "24/7 Wall St.",
        "published": "2026-06-16T16:20:05Z",
        "summary": "Jeff Bezos is back in an operating seat for the first time since stepping down from Amazon (NASDAQ:AMZN), pointing a $12 billion war chest at what he calls the engine of civilizational wealth: invention itself. In a CNBC interview on June 11, 2026, Bezos and co-CEO Vik Bajaj outlined Prometheus, a Series B round raising ... Jeff Bezos Just Raised $12 Billion. He\u2019s Betting His Newest Business Will Create the Next Elon Musk or Henry Ford",
        "bullish_score": 1,
        "bearish_score": 0,
        "importance_score": 45,
        "why_it_matters": "News appears more supportive of sentiment or growth expectations."
      },
      {
        "headline": "Who Is The World\u2019s Second Richest Person?",
        "source": "24/7 Wall St.",
        "published": "2026-06-16T16:13:45Z",
        "summary": "After SpaceX\u2019s (NASDAQ: SPCX) IPO, Elon Musk\u2019s net worth rose to $1.27 billion, making him the first trillionaire in world history (at least as far as most people know, based on inflation-adjusted dollars). His net worth has risen to $653 billion this year. That increase alone is larger than the net worth of the second-richest ... Who Is The World\u2019s Second Richest Person?",
        "bullish_score": 0,
        "bearish_score": 0,
        "importance_score": 30,
        "why_it_matters": "News impact is unclear; monitor price and volume reaction."
      }
    ]
  },
  "sentiment": {
    "available": false,
    "note": "Social sentiment sources are not configured."
  },
  "options_flow": {
    "available": false,
    "note": "Options flow scan requires a dedicated options-chain pass."
  },
  "portfolio_fit": {
    "available": true,
    "sector": null,
    "current_sector_weight": 0,
    "assessment": "Potential diversifier; evaluate correlation and volatility before adding."
  },
  "why_now": {
    "send_alert": false,
    "reason": "No clear Why Now trigger",
    "evidence": "No recent statistically meaningful change was detected.",
    "date_of_change": "2026-06-16",
    "strength": 0,
    "invalidates": "N/A",
    "triggers": []
  },
  "report": "Ticker: GOOG\nRating: Watch | Score: 65.15/100 | Confidence: 53.98/100\nBull Case: momentum and relative strength are constructive, fundamentals screen as Quality Compounder\nBear Case: volume confirmation is weak\nTechnical Outlook: trend continuation | Support: 273.1400146484375 | Resistance: 399.0400085449219\nFundamental Outlook: Quality Compounder | Forward P/E: 25.471302\nNews/Catalyst: SpaceX rockets past Amazon, eyes Microsoft in sprint toward $3 trillion\nPortfolio Fit: Potential diversifier; evaluate correlation and volatility before adding.\nWhy Now: No clear Why Now trigger | Evidence: No recent statistically meaningful change was detected.\nWhat Invalidates: N/A"
}