{
  "ticker": "TSLA",
  "generated_at": "2026-06-24T15:33:23.804656",
  "score": {
    "final_score": 29.2,
    "rating": "Avoid",
    "confidence": 21.45,
    "risk_level": "High",
    "categories": {
      "technical": 10.0,
      "momentum": 45.0,
      "volume": 0,
      "fundamental": 53.0,
      "risk": 35.0,
      "catalyst": 45.0
    },
    "technical": {
      "score": 10.0,
      "evidence": [
        "Stock is not materially extended from SMA20"
      ],
      "support": 343.25,
      "resistance": 445.2699890136719,
      "risk_reward": 1.55
    },
    "momentum": {
      "score": 45.0,
      "returns": {
        "1m": -0.10046738077076711,
        "3m": 0.0004696789379949884,
        "6m": -0.20363696969843026,
        "12m": 0.09903036581359004
      },
      "acceleration": 0.1023,
      "evidence": [
        "3m return is positive",
        "12m return is positive",
        "Momentum is accelerating"
      ]
    },
    "volume": {
      "score": 0,
      "average_volume": 45747239.05,
      "relative_volume": 0.2670932990435846,
      "accumulation_days": 4,
      "distribution_days": 4,
      "evidence": []
    },
    "fundamental": {
      "score": 53.0,
      "classification": "Fundamentally Average",
      "evidence": [
        "revenue growth is strong",
        "Valuation appears demanding versus growth"
      ]
    },
    "risk": {
      "score": 35.0,
      "risk_metrics": {
        "volatility": 0.03857013080409759,
        "annualized_volatility": 0.6122818448572437,
        "maximum_drawdown": -0.5376568011858518,
        "sharpe_ratio": 0.9112844170042903,
        "sortino_ratio": 1.4834014455323699,
        "calmar_ratio": 0.8406175955286239,
        "beta": 2.298181579618782,
        "alpha": 0.14066695971500465,
        "capm_expected_return": 0.41729594431803996,
        "actual_return": 0.5579629040330446,
        "market_return": 0.18157657689835816
      },
      "evidence": [
        "Volatility is elevated",
        "Historical drawdown is severe",
        "Beta indicates elevated market sensitivity"
      ]
    },
    "catalyst": {
      "score": 45.0,
      "evidence": [
        "analyst revision",
        "insider buying",
        "guidance change"
      ]
    },
    "explanation": "Stock is not materially extended from SMA20; 3m return is positive; 12m return is positive; Momentum is accelerating; revenue growth is strong; Valuation appears demanding versus growth"
  },
  "fundamentals": {
    "ticker": "TSLA",
    "available": true,
    "company_name": "Tesla, Inc.",
    "sector": "Consumer Cyclical",
    "industry": "Auto Manufacturers",
    "exchange": "NMS",
    "market_cap": 1436188803072.0,
    "revenue_growth": 0.158,
    "eps_growth": 0.083,
    "fcf_growth": null,
    "ebitda_growth": null,
    "gross_margin": 0.19065,
    "operating_margin": 0.04203,
    "net_margin": 0.03946,
    "roe": 0.04901,
    "roa": 0.022330001,
    "roic": null,
    "debt_to_equity": 0.18738,
    "current_ratio": 2.043,
    "quick_ratio": 1.43,
    "cash_position": 44743000064.0,
    "total_debt": 15889999872.0,
    "interest_coverage": null,
    "forward_pe": 152.96306,
    "trailing_pe": 344.5045,
    "peg": 5.79,
    "price_to_book": 17.46358,
    "price_to_sales": 14.670419,
    "enterprise_to_ebitda": 126.65,
    "enterprise_to_revenue": 14.355,
    "fcf_yield": 0.0036569006336534594,
    "institutional_ownership": 0.44928002,
    "insider_ownership": 0.18737,
    "short_interest": 76947758.0,
    "short_ratio": 1.48,
    "short_percent_float": 0.023,
    "days_to_cover": 1.48,
    "target_mean_price": 421.1561,
    "target_high_price": 600.0,
    "target_low_price": 123.0,
    "recommendation": "buy",
    "number_of_analysts": 41.0,
    "dividend_yield": null,
    "payout_ratio": 0.0,
    "next_earnings_date": "1776888000",
    "eps_current_year": 1.11,
    "eps_forward": 2.49995,
    "classification": "Fundamentally Average"
  },
  "technical_screen": {
    "rsi": 37.02655196771491,
    "macd_cross": false,
    "breakout": false,
    "new_52w_high": false,
    "relative_volume": 0.2670932990435846,
    "price_above_sma50": false,
    "price_above_sma200": false,
    "setup_type": "No clear setup",
    "support": 343.25,
    "resistance": 445.2699890136719
  },
  "earnings": {
    "next_earnings_date": "1776888000",
    "surprise_tracking": "Available",
    "beat_streak": 2,
    "miss_streak": 0,
    "average_surprise_pct": 0.04,
    "last_surprise_pct": 0.1715,
    "last_surprise_direction": "beat",
    "risk_score": 65,
    "history": [
      {
        "date": "2026-03-31",
        "eps_estimate": 0.34999,
        "eps_actual": 0.41,
        "surprise_pct": 0.1715,
        "beat": true
      },
      {
        "date": "2025-12-31",
        "eps_estimate": 0.45061,
        "eps_actual": 0.5,
        "surprise_pct": 0.1096,
        "beat": true
      },
      {
        "date": "2025-09-30",
        "eps_estimate": 0.55885,
        "eps_actual": 0.5,
        "surprise_pct": -0.105299994,
        "beat": false
      },
      {
        "date": "2025-06-30",
        "eps_estimate": 0.40451,
        "eps_actual": 0.4,
        "surprise_pct": -0.0111,
        "beat": false
      }
    ]
  },
  "catalysts": {
    "earnings_surprise": false,
    "analyst_revision": true,
    "insider_buying": true,
    "sector_strength": false,
    "major_news": false,
    "guidance_change": true,
    "bullish_news_score": 1,
    "bearish_news_score": 0,
    "institutional_ownership": 0.44928002,
    "detail": {
      "earnings": {
        "available": true,
        "history": [
          {
            "date": "2026-03-31",
            "eps_estimate": 0.34999,
            "eps_actual": 0.41,
            "surprise_pct": 0.1715,
            "beat": true
          },
          {
            "date": "2025-12-31",
            "eps_estimate": 0.45061,
            "eps_actual": 0.5,
            "surprise_pct": 0.1096,
            "beat": true
          },
          {
            "date": "2025-09-30",
            "eps_estimate": 0.55885,
            "eps_actual": 0.5,
            "surprise_pct": -0.105299994,
            "beat": false
          },
          {
            "date": "2025-06-30",
            "eps_estimate": 0.40451,
            "eps_actual": 0.4,
            "surprise_pct": -0.0111,
            "beat": false
          }
        ],
        "beat_streak": 2,
        "miss_streak": 0,
        "average_surprise_pct": 0.04,
        "last_surprise_pct": 0.1715,
        "last_surprise_direction": "beat"
      },
      "analyst_upside_pct": 10.14,
      "eps_growth_implied": 125.22
    },
    "evidence": [
      "analyst target/recommendation data is supportive",
      "insider ownership or purchase data is supportive",
      "news tone or forward EPS implies a catalyst shift"
    ]
  },
  "analyst": {
    "consensus": "buy",
    "target_mean_price": 421.1561,
    "target_high_price": 600.0,
    "target_low_price": 123.0,
    "number_of_analysts": 41.0
  },
  "insider_short_interest": {
    "insider_ownership": 0.18737,
    "institutional_ownership": 0.44928002,
    "short_interest": 76947758.0,
    "short_percent_float": 0.023,
    "days_to_cover": 1.48,
    "insider_transactions": "Unavailable from current data provider."
  },
  "news": {
    "available": true,
    "items": [
      {
        "headline": "Big Tech's $2.7 trillion AI bill comes due: Chart of the Day",
        "source": "Yahoo Finance",
        "published": "2026-06-24T10:00:00Z",
        "summary": "The \"Magnificent Seven\" plus Broadcom and Oracle have lost roughly $2.7 trillion in market value in June, according to Yahoo Finance analysis, as investors take a harder look at the companies funding the AI build-out.",
        "bullish_score": 0,
        "bearish_score": 0,
        "importance_score": 30,
        "why_it_matters": "News impact is unclear; monitor price and volume reaction."
      },
      {
        "headline": "Should You Forget Tesla and Buy SpaceX Instead?",
        "source": "Motley Fool",
        "published": "2026-06-24T14:51:00Z",
        "summary": "There's plenty of speculation about a merger, and these two companies might be an ideal operational fit, but their investment profiles differ significantly.",
        "bullish_score": 0,
        "bearish_score": 0,
        "importance_score": 30,
        "why_it_matters": "News impact is unclear; monitor price and volume reaction."
      },
      {
        "headline": "RUN Stock Surges On Partnership With Tesla, Renew Home \u2013 Sunrun CEO Says Grid Of 1800s Can\u2019t \u2018Power The Innovation Of 2026\u2019",
        "source": "Stocktwits",
        "published": "2026-06-24T14:36:42Z",
        "summary": "Sunrun, Tesla, and Renew Home entered into an agreement to deliver more than 16 gigawatts of flexible energy capacity to hyperscalers and utilities.",
        "bullish_score": 0,
        "bearish_score": 0,
        "importance_score": 30,
        "why_it_matters": "News impact is unclear; monitor price and volume reaction."
      },
      {
        "headline": "Lucid vs. Rivian: Which Is Winning the Only Race That Matters?",
        "source": "Motley Fool",
        "published": "2026-06-24T14:35:00Z",
        "summary": "It's important to track young automakers' top-line growth, but investors should really key in on another metric -- and that race has one clear leader.",
        "bullish_score": 1,
        "bearish_score": 0,
        "importance_score": 45,
        "why_it_matters": "News appears more supportive of sentiment or growth expectations."
      },
      {
        "headline": "Elon Musk\u2019s trillionaire status slips as SpaceX shares swing",
        "source": "PA Media: Money",
        "published": "2026-06-24T14:33:07Z",
        "summary": "He is now worth an estimated 962 billion dollars (\u00a3731.4 billion), as of the end of the day on Tuesday, Forbes said.",
        "bullish_score": 0,
        "bearish_score": 0,
        "importance_score": 30,
        "why_it_matters": "News impact is unclear; monitor price and volume reaction."
      }
    ]
  },
  "sentiment": {
    "available": false,
    "note": "Social sentiment sources are not configured."
  },
  "options_flow": {
    "available": false,
    "note": "Options flow scan requires a dedicated options-chain pass."
  },
  "portfolio_fit": {
    "available": true,
    "assessment": "Already held; monitor risk contribution and thesis quality."
  },
  "probability": {
    "model": "rules_to_probability_v1",
    "probability_of_outperformance": 0.456,
    "probability_pct": 45.6,
    "confidence": "High",
    "evidence": [
      "Analyst data is supportive",
      "Composite score 29.2/100"
    ],
    "note": "Heuristic probability until enough labeled outcomes exist for trained ML."
  },
  "features": {
    "final_score": 29.2,
    "technical_score": 10.0,
    "momentum_score": 45.0,
    "volume_score": 0,
    "fundamental_score": 53.0,
    "risk_score": 35.0,
    "catalyst_score": 45.0,
    "revenue_growth": 0.158,
    "eps_growth": 0.083,
    "roe": 0.04901,
    "forward_pe": 152.96306,
    "relative_volume": 0.2670932990435846,
    "breakout": false,
    "price_above_sma50": false,
    "price_above_sma200": false,
    "earnings_surprise": false,
    "analyst_revision": true,
    "major_news": false
  },
  "quant_model": {
    "returns": {
      "daily": 0.004192538487448827,
      "weekly": -0.053007718987904795,
      "monthly": -0.10046738077076711,
      "annual": 0.09903036581359004
    },
    "risk": {
      "volatility": 0.03857013080409759,
      "annualized_volatility": 0.6122818448572437,
      "maximum_drawdown": -0.5376568011858518,
      "sharpe_ratio": 0.9112844170042903,
      "sortino_ratio": 1.4834014455323699,
      "calmar_ratio": 0.8406175955286239,
      "beta": 2.298181579618782,
      "alpha": 0.14066695971500465,
      "capm_expected_return": 0.41729594431803996,
      "actual_return": 0.5579629040330446,
      "market_return": 0.18157657689835816
    },
    "capm": {
      "beta": 2.298181579618782,
      "alpha": 0.14066695971500465,
      "capm_expected_return": 0.41729594431803996,
      "actual_return": 0.5579629040330446,
      "market_return": 0.18157657689835816,
      "interpretation": "Beta 2.30: Moves roughly 130% more than the market. CAPM expected return is 41.73%; realized alpha is 14.07%, meaning positive alpha versus CAPM."
    },
    "factor_decomposition": {
      "actual_return": 0.5579629040330446,
      "components": {
        "market_component": 0.41729594431803996,
        "momentum_component": 0.02475759145339751,
        "volatility_drag": -0.07245636897144873,
        "alpha_component": 0.14066695971500465
      },
      "component_weights_pct": {
        "market_component": 63.69,
        "momentum_component": 3.78,
        "volatility_drag": 11.06,
        "alpha_component": 21.47
      },
      "interpretation": "Decomposes realized return into market risk, momentum proxy, volatility drag, and residual alpha. This is a research approximation, not proof of causality."
    },
    "trend": {
      "sma20": 408.31849365234376,
      "sma50": 404.9449981689453,
      "sma200": 417.69579971313476,
      "ema20": 402.8352666080385,
      "ema50": 404.0089942713593,
      "ema200": 396.58412944967466
    },
    "momentum": {
      "3m": 0.0004696789379949884,
      "6m": -0.20363696969843026,
      "12m": 0.09903036581359004,
      "24m": 0.0,
      "score": 50.0
    },
    "volume": {
      "average_volume": 45747239.05,
      "relative_volume": 0.2670932990435846,
      "volume_spike": false
    },
    "volatility_regime": "Normal volatility",
    "quant_score": {
      "score": 25,
      "label": "High risk / weak setup"
    }
  },
  "why_now": {
    "send_alert": false,
    "reason": "No clear Why Now trigger",
    "evidence": "No recent statistically meaningful change was detected.",
    "date_of_change": "2026-06-24",
    "strength": 0,
    "invalidates": "N/A",
    "triggers": []
  },
  "report": "Ticker: TSLA\nRating: Avoid | Score: 29.2/100 | Confidence: 21.45/100\nBull Case: No decisive bull case yet.\nBear Case: risk score is elevated, valuation is demanding, volume confirmation is weak\nTechnical Outlook: No clear setup | Support: 343.25 | Resistance: 445.2699890136719\nFundamental Outlook: Fundamentally Average | Forward P/E: 152.96306\nNews/Catalyst: Big Tech's $2.7 trillion AI bill comes due: Chart of the Day\nPortfolio Fit: Already held; monitor risk contribution and thesis quality.\nWhy Now: No clear Why Now trigger | Evidence: No recent statistically meaningful change was detected.\nWhat Invalidates: N/A"
}