{"cached_at": 1781453625.6320925, "data": {"ticker": "APTV", "available": true, "company_name": "Aptiv PLC", "sector": "Consumer Cyclical", "industry": "Auto Parts", "exchange": "NYQ", "market_cap": 14400777216.0, "revenue_growth": 0.054, "eps_growth": null, "fcf_growth": null, "ebitda_growth": null, "gross_margin": 0.18922001, "operating_margin": 0.0987, "net_margin": 0.01767, "roe": 0.040799998, "roa": 0.05698, "roic": null, "debt_to_equity": 1.03823, "current_ratio": 2.115, "quick_ratio": 1.516, "cash_position": 3172999936.0, "total_debt": 9886000128.0, "interest_coverage": null, "forward_pe": 9.976061, "trailing_pe": 40.505955, "peg": 1.09, "price_to_book": 1.5650874, "price_to_sales": 0.6970704, "enterprise_to_ebitda": 6.72, "enterprise_to_revenue": 1.036, "fcf_yield": 0.07576847941149345, "institutional_ownership": 1.02211, "insider_ownership": 0.00821, "short_interest": 9059477.0, "short_ratio": 2.26, "short_percent_float": 0.0582, "days_to_cover": 2.26, "target_mean_price": 78.21053, "target_high_price": 94.0, "target_low_price": 65.0, "recommendation": "strong_buy", "number_of_analysts": 19.0, "dividend_yield": null, "payout_ratio": 0.0, "next_earnings_date": "1777984200", "eps_current_year": 1.68, "eps_forward": 6.82133, "classification": "Fundamentally Average"}}