{"cached_at": 1782859918.6667857, "data": {"ticker": "DELL", "available": true, "company_name": "Dell Technologies Inc.", "sector": "Technology", "industry": "Computer Hardware", "exchange": "NYQ", "market_cap": 278784606208.0, "revenue_growth": 0.875, "eps_growth": 2.825, "fcf_growth": null, "ebitda_growth": null, "gross_margin": 0.19212, "operating_margin": 0.088570006, "net_margin": 0.062750004, "roe": null, "roa": 0.07004, "roic": null, "debt_to_equity": null, "current_ratio": 0.946, "quick_ratio": 0.612, "cash_position": 11580999680.0, "total_debt": 31924000768.0, "interest_coverage": null, "forward_pe": 20.159006, "trailing_pe": 34.35191, "peg": 0.66, "price_to_book": -199.47295, "price_to_sales": 2.080451, "enterprise_to_ebitda": 20.551, "enterprise_to_revenue": 2.157, "fcf_yield": 0.019492198202456068, "institutional_ownership": 0.82405, "insider_ownership": 0.07651, "short_interest": 15809739.0, "short_ratio": 1.33, "short_percent_float": 0.0523, "days_to_cover": 1.33, "target_mean_price": 485.08698, "target_high_price": 700.0, "target_low_price": 213.0, "recommendation": "buy", "number_of_analysts": 23.0, "dividend_yield": 0.61, "payout_ratio": 0.1757, "next_earnings_date": "1788465600", "eps_current_year": 12.56, "eps_forward": 21.40284, "classification": "Fundamentally Strong"}}